.gitignore
.gitmodules
LICENSE
README.txt
TODO
bootstrap
buildout.cfg
license.rdf
setup.py
cc/__init__.py
cc.license.egg-info/PKG-INFO
cc.license.egg-info/SOURCES.txt
cc.license.egg-info/dependency_links.txt
cc.license.egg-info/entry_points.txt
cc.license.egg-info/not-zip-safe
cc.license.egg-info/requires.txt
cc.license.egg-info/top_level.txt
cc/license/__init__.py
cc/license/_lib/__init__.py
cc/license/_lib/classes.py
cc/license/_lib/exceptions.py
cc/license/_lib/functions.py
cc/license/_lib/interfaces.py
cc/license/_lib/rdf_helper.py
cc/license/formatters/__init__.py
cc/license/formatters/classes.py
cc/license/formatters/templates/html_rdfa.xml
cc/license/jurisdictions/__init__.py
cc/license/jurisdictions/classes.py
cc/license/selectors/__init__.py
cc/license/selectors/classes.py
cc/license/tests/__init__.py
cc/license/tests/test_cc_license.py
cc/license/tests/test_formatters.py
cc/license/tests/test_jurisdictions.py
cc/license/tests/test_lib.py
cc/license/tests/test_licenses.py
cc/license/tests/test_questions.py
cc/license/tests/test_selectors.py
cc/license/tests/schemata/html_rdfa.relax.xml