Metadata-Version: 1.0
Name: cc.license
Version: 0.02
Summary: License selection based on ccREL-based metadata.
Home-page: http://wiki.creativecommons.org/CcLicense
Author: Creative Commons
Author-email: software@creativecommons.org
License: MIT
Platform: UNKNOWN
